setup.py
dataflow_xent/__init__.py
dataflow_xent/compute_entropy.py
dataflow_xent/cross_sample_entropy_pipeline.py
dataflow_xent/cross_sample_entropy_pipeline_vai.py
dataflow_xent/filter_row.py
dataflow_xent/patient_data.py
dataflow_xent.egg-info/PKG-INFO
dataflow_xent.egg-info/SOURCES.txt
dataflow_xent.egg-info/dependency_links.txt
dataflow_xent.egg-info/requires.txt
dataflow_xent.egg-info/top_level.txt
dataflow_xent/xent/__init__.py
dataflow_xent/xent/xsampent.py