Metadata-Version: 2.1
Name: dataflow-xent
Version: 0.0.3
Summary: Package to be used inside cross entropy beam pipeline
Requires-Python: >=3.7, <4
